archivooor/__init__.py
archivooor/__main__.py
archivooor/archiver.py
archivooor/cli.py
archivooor/exceptions.py
archivooor/key_utils.py
archivooor-0.0.8.dist-info/METADATA
archivooor-0.0.8.dist-info/WHEEL
archivooor-0.0.8.dist-info/entry_points.txt
archivooor-0.0.8.dist-info/licenses/LICENSE
archivooor-0.0.8.dist-info/RECORD
