Metadata-Version: 2.4
Name: archivooor
Version: 0.0.8
Summary: A Python package to submit web pages to the Wayback Machine for archiving.
Project-URL: Homepage, https://github.com/Barabazs/archivooor
Project-URL: Repository, https://github.com/Barabazs/archivooor
Author-email: Barabazs <31799121+Barabazs@users.noreply.github.com>
License: MIT
License-File: LICENSE
Requires-Python: <4.0,>=3.9
Requires-Dist: click>=8.1.8
Requires-Dist: keyring>=25.6.0
Requires-Dist: requests>=2.32.3
Requires-Dist: urllib3>=2.3.0
